{
  "__inputs": [
    {
      "name": "DS_PROMETHEUS",
      "label": "prometheus",
      "description": "",
      "type": "datasource",
      "pluginId": "prometheus",
      "pluginName": "Prometheus"
    }
  ],
  "__requires": [
    {
      "type": "grafana",
      "id": "grafana",
      "name": "Grafana",
      "version": "7.5.2"
    },
    {
      "type": "panel",
      "id": "grafana-piechart-panel",
      "name": "Pie Chart",
      "version": "1.6.1"
    },
    {
      "type": "panel",
      "id": "graph",
      "name": "Graph",
      "version": ""
    },
    {
      "type": "datasource",
      "id": "prometheus",
      "name": "Prometheus",
      "version": "1.0.0"
    }
  ],
  "annotations": {
    "list": [
      {
        "builtIn": 1,
        "datasource": "-- Grafana --",
        "enable": true,
        "hide": true,
        "iconColor": "rgba(0, 211, 255, 1)",
        "name": "Annotations & Alerts",
        "type": "dashboard"
      }
    ]
  },
  "editable": true,
  "gnetId": null,
  "graphTooltip": 0,
  "id": null,
  "iteration": 1647160365420,
  "links": [],
  "panels": [
    {
      "aliasColors": {},
      "breakPoint": "50%",
      "cacheTimeout": null,
      "combine": {
        "label": "Others",
        "threshold": 0
      },
      "datasource": "${DS_PROMETHEUS}",
      "fieldConfig": {
        "defaults": {},
        "overrides": []
      },
      "fontSize": "80%",
      "format": "short",
      "gridPos": {
        "h": 9,
        "w": 12,
        "x": 0,
        "y": 0
      },
      "id": 11,
      "interval": null,
      "legend": {
        "percentage": true,
        "show": true,
        "values": false
      },
      "legendType": "On graph",
      "links": [],
      "nullPointMode": "connected",
      "pieType": "pie",
      "pluginVersion": "7.5.2",
      "strokeWidth": 1,
      "targets": [
        {
          "exemplar": true,
          "expr": "rate(systemd_resolved_cache_hits_total{instance=\"[[instance]]\"}[$__rate_interval])",
          "format": "time_series",
          "instant": false,
          "interval": "60",
          "legendFormat": "Cache Hits",
          "refId": "A"
        },
        {
          "exemplar": true,
          "expr": "rate(systemd_resolved_cache_misses_total{instance=\"[[instance]]\"}[$__rate_interval])",
          "hide": false,
          "instant": false,
          "interval": "60",
          "legendFormat": "Cache Misses",
          "refId": "B"
        }
      ],
      "timeFrom": null,
      "timeShift": null,
      "title": "Current Cache Hit Rate",
      "transparent": true,
      "type": "grafana-piechart-panel",
      "valueName": "current"
    },
    {
      "aliasColors": {},
      "bars": false,
      "dashLength": 10,
      "dashes": false,
      "datasource": "${DS_PROMETHEUS}",
      "fieldConfig": {
        "defaults": {},
        "overrides": []
      },
      "fill": 1,
      "fillGradient": 0,
      "gridPos": {
        "h": 9,
        "w": 12,
        "x": 12,
        "y": 0
      },
      "hiddenSeries": false,
      "id": 12,
      "legend": {
        "avg": false,
        "current": true,
        "max": false,
        "min": false,
        "show": true,
        "total": false,
        "values": true
      },
      "lines": true,
      "linewidth": 1,
      "nullPointMode": "null",
      "options": {
        "alertThreshold": true
      },
      "percentage": false,
      "pluginVersion": "7.5.2",
      "pointradius": 2,
      "points": false,
      "renderer": "flot",
      "seriesOverrides": [],
      "spaceLength": 10,
      "stack": false,
      "steppedLine": false,
      "targets": [
        {
          "exemplar": true,
          "expr": "rate(systemd_resolved_cache_hits_total{instance=\"[[instance]]\"}[$__rate_interval]) / (\nrate(systemd_resolved_cache_hits_total{instance=\"[[instance]]\"}[$__rate_interval]) + rate(systemd_resolved_cache_misses_total{instance=\"[[instance]]\"}[$__rate_interval])\n)",
          "interval": "60",
          "legendFormat": "Cache Hit Rate",
          "refId": "A"
        }
      ],
      "thresholds": [],
      "timeFrom": null,
      "timeRegions": [],
      "timeShift": null,
      "title": "Cache Hit Rate",
      "tooltip": {
        "shared": true,
        "sort": 0,
        "value_type": "individual"
      },
      "type": "graph",
      "xaxis": {
        "buckets": null,
        "mode": "time",
        "name": null,
        "show": true,
        "values": []
      },
      "yaxes": [
        {
          "$$hashKey": "object:476",
          "format": "percentunit",
          "label": null,
          "logBase": 1,
          "max": null,
          "min": null,
          "show": true
        },
        {
          "$$hashKey": "object:477",
          "format": "short",
          "label": null,
          "logBase": 1,
          "max": null,
          "min": null,
          "show": true
        }
      ],
      "yaxis": {
        "align": false,
        "alignLevel": null
      }
    },
    {
      "aliasColors": {},
      "bars": false,
      "dashLength": 10,
      "dashes": false,
      "datasource": "${DS_PROMETHEUS}",
      "fieldConfig": {
        "defaults": {},
        "overrides": []
      },
      "fill": 1,
      "fillGradient": 0,
      "gridPos": {
        "h": 9,
        "w": 12,
        "x": 0,
        "y": 9
      },
      "hiddenSeries": false,
      "id": 2,
      "legend": {
        "avg": false,
        "current": true,
        "max": false,
        "min": false,
        "show": true,
        "total": false,
        "values": true
      },
      "lines": true,
      "linewidth": 1,
      "nullPointMode": "null",
      "options": {
        "alertThreshold": true
      },
      "percentage": false,
      "pluginVersion": "7.5.2",
      "pointradius": 2,
      "points": false,
      "renderer": "flot",
      "seriesOverrides": [],
      "spaceLength": 10,
      "stack": false,
      "steppedLine": false,
      "targets": [
        {
          "exemplar": true,
          "expr": "rate(systemd_resolved_cache_hits_total{instance=\"[[instance]]\"}[$__rate_interval])",
          "interval": "",
          "legendFormat": "Cache Hits",
          "refId": "A"
        }
      ],
      "thresholds": [],
      "timeFrom": null,
      "timeRegions": [],
      "timeShift": null,
      "title": "Cache Hits",
      "tooltip": {
        "shared": true,
        "sort": 0,
        "value_type": "individual"
      },
      "type": "graph",
      "xaxis": {
        "buckets": null,
        "mode": "time",
        "name": null,
        "show": true,
        "values": []
      },
      "yaxes": [
        {
          "$$hashKey": "object:433",
          "format": "short",
          "label": null,
          "logBase": 1,
          "max": null,
          "min": null,
          "show": true
        },
        {
          "$$hashKey": "object:434",
          "format": "short",
          "label": null,
          "logBase": 1,
          "max": null,
          "min": null,
          "show": true
        }
      ],
      "yaxis": {
        "align": false,
        "alignLevel": null
      }
    },
    {
      "aliasColors": {},
      "bars": false,
      "dashLength": 10,
      "dashes": false,
      "datasource": "${DS_PROMETHEUS}",
      "fieldConfig": {
        "defaults": {},
        "overrides": []
      },
      "fill": 1,
      "fillGradient": 0,
      "gridPos": {
        "h": 9,
        "w": 12,
        "x": 12,
        "y": 9
      },
      "hiddenSeries": false,
      "id": 4,
      "legend": {
        "avg": false,
        "current": true,
        "max": false,
        "min": false,
        "show": true,
        "total": false,
        "values": true
      },
      "lines": true,
      "linewidth": 1,
      "nullPointMode": "null",
      "options": {
        "alertThreshold": true
      },
      "percentage": false,
      "pluginVersion": "7.5.2",
      "pointradius": 2,
      "points": false,
      "renderer": "flot",
      "seriesOverrides": [],
      "spaceLength": 10,
      "stack": false,
      "steppedLine": false,
      "targets": [
        {
          "exemplar": true,
          "expr": "rate(systemd_resolved_cache_misses_total{instance=\"[[instance]]\"}[$__rate_interval])",
          "interval": "",
          "legendFormat": "Cache Misses",
          "refId": "A"
        }
      ],
      "thresholds": [],
      "timeFrom": null,
      "timeRegions": [],
      "timeShift": null,
      "title": "Cache Misses",
      "tooltip": {
        "shared": true,
        "sort": 0,
        "value_type": "individual"
      },
      "type": "graph",
      "xaxis": {
        "buckets": null,
        "mode": "time",
        "name": null,
        "show": true,
        "values": []
      },
      "yaxes": [
        {
          "$$hashKey": "object:355",
          "format": "short",
          "label": null,
          "logBase": 1,
          "max": null,
          "min": null,
          "show": true
        },
        {
          "$$hashKey": "object:356",
          "format": "short",
          "label": null,
          "logBase": 1,
          "max": null,
          "min": null,
          "show": true
        }
      ],
      "yaxis": {
        "align": false,
        "alignLevel": null
      }
    },
    {
      "aliasColors": {},
      "bars": false,
      "dashLength": 10,
      "dashes": false,
      "datasource": "${DS_PROMETHEUS}",
      "fieldConfig": {
        "defaults": {},
        "overrides": []
      },
      "fill": 1,
      "fillGradient": 0,
      "gridPos": {
        "h": 9,
        "w": 12,
        "x": 0,
        "y": 18
      },
      "hiddenSeries": false,
      "id": 5,
      "legend": {
        "avg": false,
        "current": true,
        "max": false,
        "min": false,
        "show": true,
        "total": false,
        "values": true
      },
      "lines": true,
      "linewidth": 1,
      "nullPointMode": "null",
      "options": {
        "alertThreshold": true
      },
      "percentage": false,
      "pluginVersion": "7.5.2",
      "pointradius": 2,
      "points": false,
      "renderer": "flot",
      "seriesOverrides": [],
      "spaceLength": 10,
      "stack": false,
      "steppedLine": false,
      "targets": [
        {
          "exemplar": true,
          "expr": "rate(systemd_resolved_transactions_total{instance=\"[[instance]]\"}[$__rate_interval])",
          "interval": "",
          "legendFormat": "Transactions",
          "refId": "A"
        }
      ],
      "thresholds": [],
      "timeFrom": null,
      "timeRegions": [],
      "timeShift": null,
      "title": "Transactions",
      "tooltip": {
        "shared": true,
        "sort": 0,
        "value_type": "individual"
      },
      "type": "graph",
      "xaxis": {
        "buckets": null,
        "mode": "time",
        "name": null,
        "show": true,
        "values": []
      },
      "yaxes": [
        {
          "$$hashKey": "object:585",
          "format": "short",
          "label": null,
          "logBase": 1,
          "max": null,
          "min": null,
          "show": true
        },
        {
          "$$hashKey": "object:586",
          "format": "short",
          "label": null,
          "logBase": 1,
          "max": null,
          "min": null,
          "show": true
        }
      ],
      "yaxis": {
        "align": false,
        "alignLevel": null
      }
    },
    {
      "aliasColors": {},
      "bars": false,
      "dashLength": 10,
      "dashes": false,
      "datasource": "${DS_PROMETHEUS}",
      "fieldConfig": {
        "defaults": {},
        "overrides": []
      },
      "fill": 1,
      "fillGradient": 0,
      "gridPos": {
        "h": 9,
        "w": 12,
        "x": 12,
        "y": 18
      },
      "hiddenSeries": false,
      "id": 6,
      "legend": {
        "avg": false,
        "current": true,
        "max": false,
        "min": false,
        "show": true,
        "total": false,
        "values": true
      },
      "lines": true,
      "linewidth": 1,
      "nullPointMode": "null",
      "options": {
        "alertThreshold": true
      },
      "percentage": false,
      "pluginVersion": "7.5.2",
      "pointradius": 2,
      "points": false,
      "renderer": "flot",
      "seriesOverrides": [],
      "spaceLength": 10,
      "stack": false,
      "steppedLine": false,
      "targets": [
        {
          "exemplar": true,
          "expr": "systemd_resolved_current_cache_size{instance=\"[[instance]]\"}",
          "interval": "",
          "legendFormat": "Current Cache Size",
          "refId": "A"
        }
      ],
      "thresholds": [],
      "timeFrom": null,
      "timeRegions": [],
      "timeShift": null,
      "title": "Current Cache Size",
      "tooltip": {
        "shared": true,
        "sort": 0,
        "value_type": "individual"
      },
      "type": "graph",
      "xaxis": {
        "buckets": null,
        "mode": "time",
        "name": null,
        "show": true,
        "values": []
      },
      "yaxes": [
        {
          "$$hashKey": "object:509",
          "format": "short",
          "label": null,
          "logBase": 1,
          "max": null,
          "min": null,
          "show": true
        },
        {
          "$$hashKey": "object:510",
          "format": "short",
          "label": null,
          "logBase": 1,
          "max": null,
          "min": null,
          "show": true
        }
      ],
      "yaxis": {
        "align": false,
        "alignLevel": null
      }
    },
    {
      "aliasColors": {},
      "bars": false,
      "dashLength": 10,
      "dashes": false,
      "datasource": "${DS_PROMETHEUS}",
      "description": "note:make sure gather-dnssec option is enabled",
      "fieldConfig": {
        "defaults": {},
        "overrides": []
      },
      "fill": 1,
      "fillGradient": 0,
      "gridPos": {
        "h": 8,
        "w": 24,
        "x": 0,
        "y": 27
      },
      "hiddenSeries": false,
      "id": 10,
      "legend": {
        "avg": false,
        "current": true,
        "max": false,
        "min": false,
        "show": true,
        "total": false,
        "values": true
      },
      "lines": true,
      "linewidth": 1,
      "nullPointMode": "null",
      "options": {
        "alertThreshold": true
      },
      "percentage": false,
      "pluginVersion": "7.5.2",
      "pointradius": 2,
      "points": false,
      "renderer": "flot",
      "seriesOverrides": [],
      "spaceLength": 10,
      "stack": true,
      "steppedLine": false,
      "targets": [
        {
          "exemplar": true,
          "expr": "rate(systemd_resolved_dnssec_bogus_total{instance=\"[[instance]]\"}[$__rate_interval])",
          "interval": "",
          "legendFormat": "Bugus",
          "refId": "A"
        },
        {
          "exemplar": true,
          "expr": "rate(systemd_resolved_dnssec_insecure_total{instance=\"[[instance]]\"}[$__rate_interval])",
          "hide": false,
          "interval": "",
          "legendFormat": "Insecure",
          "refId": "B"
        },
        {
          "exemplar": true,
          "expr": "rate(systemd_resolved_dnssec_secure_total{instance=\"[[instance]]\"}[$__rate_interval])",
          "hide": false,
          "interval": "",
          "legendFormat": "Secure",
          "refId": "C"
        },
        {
          "exemplar": true,
          "expr": "rate(systemd_resolved_dnssec_indeterminate_total{instance=\"[[instance]]\"}[$__rate_interval])",
          "hide": false,
          "interval": "",
          "legendFormat": "Indeterminate",
          "refId": "D"
        }
      ],
      "thresholds": [],
      "timeFrom": null,
      "timeRegions": [],
      "timeShift": null,
      "title": "DNSSEC Verdicts",
      "tooltip": {
        "shared": true,
        "sort": 2,
        "value_type": "individual"
      },
      "type": "graph",
      "xaxis": {
        "buckets": null,
        "mode": "time",
        "name": null,
        "show": true,
        "values": []
      },
      "yaxes": [
        {
          "$$hashKey": "object:663",
          "format": "short",
          "label": null,
          "logBase": 1,
          "max": null,
          "min": null,
          "show": true
        },
        {
          "$$hashKey": "object:664",
          "format": "short",
          "label": null,
          "logBase": 1,
          "max": null,
          "min": null,
          "show": true
        }
      ],
      "yaxis": {
        "align": false,
        "alignLevel": null
      }
    }
  ],
  "schemaVersion": 27,
  "style": "dark",
  "tags": [],
  "templating": {
    "list": [
      {
        "current": {
          "selected": false,
          "text": "prometheus",
          "value": "prometheus"
        },
        "description": null,
        "error": null,
        "hide": 0,
        "includeAll": false,
        "label": null,
        "multi": false,
        "name": "PROMETHEUS_DS",
        "options": [],
        "query": "prometheus",
        "refresh": 1,
        "regex": "",
        "skipUrlSync": false,
        "type": "datasource"
      },
      {
        "allValue": null,
        "current": {},
        "datasource": "${DS_PROMETHEUS}",
        "definition": "label_values(systemd_resolved_transactions_total,instance)",
        "description": null,
        "error": null,
        "hide": 0,
        "includeAll": false,
        "label": "instance",
        "multi": false,
        "name": "instance",
        "options": [],
        "query": {
          "query": "label_values(systemd_resolved_transactions_total,instance)",
          "refId": "StandardVariableQuery"
        },
        "refresh": 1,
        "regex": "",
        "skipUrlSync": false,
        "sort": 0,
        "tagValuesQuery": "",
        "tags": [],
        "tagsQuery": "",
        "type": "query",
        "useTags": false
      }
    ]
  },
  "time": {
    "from": "now-6h",
    "to": "now"
  },
  "timepicker": {},
  "timezone": "",
  "title": "Systemd Resolved Exporter",
  "uid": "systemd-resolved-exporter",
  "version": 9
}
